{
  "phase": "Q179",
  "name": "Blind Reproducibility Protocol (v3)",
  "n_tasks": 12,
  "tasks": [
    {
      "name": "CAPITAL_FR_DE",
      "visibility": 1.0,
      "amplitude": 0.497837,
      "p0_target": 0.9957,
      "p1_target": 0.1151,
      "cosine_01": 0.0445,
      "p_curve": [
        0.9957,
        0.0405,
        0.0,
        0.0001,
        0.036,
        0.0043,
        0.0,
        0.0,
        0.0,
        0.0,
        0.0,
        0.0,
        0.0,
        0.0001,
        0.6874,
        0.9957
      ]
    },
    {
      "name": "COLOR_sky_grass",
      "visibility": 1.0,
      "amplitude": 0.499671,
      "p0_target": 0.9993,
      "p1_target": 0.0426,
      "cosine_01": -0.1265,
      "p_curve": [
        0.9993,
        0.0227,
        0.0,
        0.0115,
        0.0195,
        0.0001,
        0.0,
        0.0,
        0.0002,
        0.0,
        0.0,
        0.0,
        0.0,
        0.0,
        0.0739,
        0.9993
      ]
    },
    {
      "name": "CODE_return_pass",
      "visibility": 1.0,
      "amplitude": 0.407721,
      "p0_target": 0.8154,
      "p1_target": 0.0,
      "cosine_01": 0.0714,
      "p_curve": [
        0.8154,
        0.0006,
        0.0015,
        0.0,
        0.0,
        0.0,
        0.0,
        0.0,
        0.0,
        0.0,
        0.0,
        0.0,
        0.0,
        0.0,
        0.0,
        0.8154
      ]
    },
    {
      "name": "PARITY_even_odd",
      "visibility": 1.0,
      "amplitude": 0.253105,
      "p0_target": 0.5062,
      "p1_target": 0.0005,
      "cosine_01": 0.0233,
      "p_curve": [
        0.5062,
        0.0007,
        0.0,
        0.0,
        0.0016,
        0.0,
        0.0,
        0.0,
        0.0,
        0.0,
        0.0,
        0.0,
        0.0,
        0.0,
        0.0,
        0.5062
      ]
    },
    {
      "name": "ANIMAL_cat_dog",
      "visibility": 1.0,
      "amplitude": 0.096759,
      "p0_target": 0.1935,
      "p1_target": 0.0021,
      "cosine_01": -0.0186,
      "p_curve": [
        0.1935,
        0.0205,
        0.0,
        0.1733,
        0.032,
        0.0009,
        0.0034,
        0.0,
        0.0,
        0.0,
        0.0,
        0.0,
        0.0,
        0.0,
        0.0007,
        0.1935
      ]
    },
    {
      "name": "SEASON_summer_winter",
      "visibility": 1.0,
      "amplitude": 0.499288,
      "p0_target": 0.9986,
      "p1_target": 0.0006,
      "cosine_01": 0.0499,
      "p_curve": [
        0.9986,
        0.0081,
        0.0001,
        0.0003,
        0.016,
        0.0,
        0.0,
        0.0,
        0.0,
        0.0,
        0.0,
        0.0,
        0.0,
        0.0,
        0.0027,
        0.9986
      ]
    },
    {
      "name": "DIRECTION_north_south",
      "visibility": 1.0,
      "amplitude": 0.499691,
      "p0_target": 0.9994,
      "p1_target": 0.0003,
      "cosine_01": -0.0573,
      "p_curve": [
        0.9994,
        0.0043,
        0.0,
        0.0042,
        0.0011,
        0.0,
        0.0,
        0.0,
        0.0,
        0.0,
        0.0001,
        0.0,
        0.0,
        0.0,
        0.1916,
        0.9994
      ]
    },
    {
      "name": "SIZE_big_small",
      "visibility": 1.0,
      "amplitude": 0.499238,
      "p0_target": 0.9985,
      "p1_target": 0.0216,
      "cosine_01": 0.0321,
      "p_curve": [
        0.9985,
        0.1375,
        0.0006,
        0.0087,
        0.0019,
        0.0,
        0.0,
        0.0,
        0.0,
        0.0,
        0.0,
        0.0,
        0.0,
        0.0,
        0.0166,
        0.9985
      ]
    },
    {
      "name": "TEMP_hot_cold",
      "visibility": 1.0,
      "amplitude": 0.499264,
      "p0_target": 0.9985,
      "p1_target": 0.0,
      "cosine_01": -0.0438,
      "p_curve": [
        0.9985,
        0.099,
        0.0,
        0.0,
        0.1245,
        0.0,
        0.0,
        0.0,
        0.0,
        0.0,
        0.0,
        0.0,
        0.0,
        0.0,
        0.0001,
        0.9985
      ]
    },
    {
      "name": "BOOL_true_false",
      "visibility": 1.0,
      "amplitude": 0.499411,
      "p0_target": 0.9988,
      "p1_target": 0.0201,
      "cosine_01": -0.007,
      "p_curve": [
        0.9988,
        0.0197,
        0.0007,
        0.0017,
        0.015,
        0.0001,
        0.0,
        0.0,
        0.0,
        0.0,
        0.0,
        0.0,
        0.0002,
        0.0,
        0.0015,
        0.9988
      ]
    },
    {
      "name": "FOOD_sweet_salty",
      "visibility": 1.0,
      "amplitude": 0.131295,
      "p0_target": 0.2626,
      "p1_target": 0.0,
      "cosine_01": 0.1019,
      "p_curve": [
        0.2626,
        0.0003,
        0.0,
        0.0,
        0.0,
        0.0,
        0.0,
        0.0,
        0.0,
        0.0,
        0.0,
        0.0,
        0.0,
        0.0,
        0.0019,
        0.2626
      ]
    },
    {
      "name": "SPEED_fast_slow",
      "visibility": 1.0,
      "amplitude": 0.488494,
      "p0_target": 0.977,
      "p1_target": 0.2306,
      "cosine_01": -0.0426,
      "p_curve": [
        0.977,
        0.0001,
        0.0,
        0.0002,
        0.0035,
        0.0003,
        0.0,
        0.0,
        0.0,
        0.0,
        0.0,
        0.0,
        0.0,
        0.0,
        0.0006,
        0.977
      ]
    }
  ],
  "summary": {
    "visibility_mean": 1.0,
    "visibility_std": 0.0,
    "pass_rate_pct": 100.0,
    "amplitude_mean": 0.405981,
    "amplitude_cv": 0.364,
    "verdict": "UNIVERSAL: interference in 12/12 tasks (100%)"
  },
  "elapsed": 367.67
}